src/__init__.py
pigeonpy-0.0.0.dist-info/METADATA
pigeonpy-0.0.0.dist-info/WHEEL
pigeonpy-0.0.0.dist-info/licenses/LICENSE
pigeonpy-0.0.0.dist-info/RECORD
