Metadata-Version: 2.4
Name: pigeonpy
Version: 0.0.0
Summary: pigeonpy
Project-URL: Documentation, https://pigeonpy.rtfd.io
Project-URL: Homepage, https://pigeonpy.uk.to/pigeonpy
Project-URL: Issues / Bugs, https://github.com/thatgaypigeonpy/pigeonpy/issues
Project-URL: PyPI, https://pypi.org/project/pigeonpy
Project-URL: Support Server, https://discord.gg/aB4Bw5pyTS
Author-email: thatgaypigeonpy <pigeonpy43.stuff@gmail.com>
License-Expression: MIT
License-File: LICENSE
Classifier: Development Status :: 1 - Planning
Classifier: Intended Audience :: Developers
Classifier: License :: OSI Approved
Classifier: License :: OSI Approved :: MIT License
Classifier: Natural Language :: English
Classifier: Operating System :: OS Independent
Classifier: Programming Language :: Python
Classifier: Programming Language :: Python :: 3.8
Classifier: Programming Language :: Python :: 3.9
Classifier: Programming Language :: Python :: 3.10
Classifier: Programming Language :: Python :: 3.11
Classifier: Programming Language :: Python :: 3.12
Classifier: Topic :: Other/Nonlisted Topic
Classifier: Topic :: Software Development
Classifier: Topic :: Software Development :: Libraries
Classifier: Topic :: Software Development :: Libraries :: Python Modules
Classifier: Typing :: Typed
Requires-Python: >=3.8
